powertrain_build/__init__.py
powertrain_build/__main__.py
powertrain_build/a2l.py
powertrain_build/a2l_merge.py
powertrain_build/a2l_templates.py
powertrain_build/build.py
powertrain_build/build_defs.py
powertrain_build/build_proj_config.py
powertrain_build/check_interface.py
powertrain_build/cli.py
powertrain_build/config.py
powertrain_build/core.py
powertrain_build/core_dummy.py
powertrain_build/create_conversion_table.py
powertrain_build/dids.py
powertrain_build/dummy.py
powertrain_build/dummy_spm.py
powertrain_build/environmentcheck.py
powertrain_build/ext_dbg.py
powertrain_build/ext_var.py
powertrain_build/feature_configs.py
powertrain_build/gen_allsysteminfo.py
powertrain_build/gen_label_split.py
powertrain_build/handcode_replacer.py
powertrain_build/html_report.py
powertrain_build/memory_section.py
powertrain_build/nvm_def.py
powertrain_build/problem_logger.py
powertrain_build/pt_matlab.py
powertrain_build/pt_win32.py
powertrain_build/replace_compu_tab_ref.py
powertrain_build/rte_dummy.py
powertrain_build/sched_funcs.py
powertrain_build/signal.py
powertrain_build/signal_if_html_rep.py
powertrain_build/signal_if_html_rep_all.py
powertrain_build/signal_incons_html_rep.py
powertrain_build/signal_incons_html_rep_all.py
powertrain_build/signal_incons_html_rep_base.py
powertrain_build/signal_inconsistency_check.py
powertrain_build/signal_interfaces.py
powertrain_build/types.py
powertrain_build/unit_configs.py
powertrain_build/user_defined_types.py
powertrain_build/versioncheck.py
powertrain_build/wrapper.py
powertrain_build/xlrd_csv.py
powertrain_build/interface/__init__.py
powertrain_build/interface/application.py
powertrain_build/interface/base.py
powertrain_build/interface/csp_api.py
powertrain_build/interface/device_proxy.py
powertrain_build/interface/ems.py
powertrain_build/interface/export_global_vars.py
powertrain_build/interface/generate_adapters.py
powertrain_build/interface/generate_hi_interface.py
powertrain_build/interface/generate_service.py
powertrain_build-1.13.1.dist-info/licenses/AUTHORS
powertrain_build-1.13.1.dist-info/licenses/LICENSE
powertrain_build-1.13.1.dist-info/licenses/NOTICE
powertrain_build-1.13.1.dist-info/METADATA
powertrain_build-1.13.1.dist-info/WHEEL
powertrain_build-1.13.1.dist-info/entry_points.txt
powertrain_build-1.13.1.dist-info/pbr.json
powertrain_build-1.13.1.dist-info/top_level.txt
powertrain_build-1.13.1.dist-info/RECORD
