Metadata-Version: 2.4
Name: powertrain-build
Version: 1.13.1
Summary: A Continuous Integration (CI) build system testing all configurations where a Simulink model is used.
Home-page: https://opendev.org/volvocars/powertrain-build
Download-URL: https://pypi.org/project/powertrain-build/
Author: Henrik Wahlqvist
Author-email: henrik.wahlqvist@volvocars.com
License: Apache License, Version 2.0
Classifier: Development Status :: 5 - Production/Stable
Classifier: Environment :: Console
Classifier: Intended Audience :: Developers
Classifier: License :: Other/Proprietary License
Classifier: Natural Language :: English
Classifier: Operating System :: OS Independent
Classifier: Programming Language :: Python :: 3.6
Classifier: Programming Language :: Python :: 3.13
Classifier: Topic :: Software Development :: Build Tools
Classifier: Topic :: Software Development :: Code Generators
Classifier: Topic :: Software Development :: Embedded Systems
License-File: LICENSE
License-File: NOTICE
License-File: AUTHORS
Requires-Dist: gitpython>=3.1.8
Requires-Dist: pbr>=6.0.0
Requires-Dist: certifi==2024.7.4
Requires-Dist: requests==2.27.1; python_version == "3.6"
Requires-Dist: ruamel.yaml.clib==0.2.7; python_version == "3.6"
Requires-Dist: ruamel.yaml==0.17.21; python_version == "3.6"
Requires-Dist: requests==2.32.3; python_version > "3.6"
Requires-Dist: ruamel.yaml==0.18.6; python_version > "3.6"
Requires-Dist: voluptuous>=0.14.0; python_version >= "3.7"
Requires-Dist: voluptuous<0.14.0,>=0.11.7; python_version < "3.7"
Requires-Dist: scipy==1.5.4; python_version < "3.8"
Requires-Dist: scipy==1.9.1; python_version == "3.8" or python_version == "3.9" or python_version == "3.10"
Requires-Dist: scipy==1.14.1; python_version >= "3.11"
Requires-Dist: importlib-resources==5.4.0; python_version < "3.9"
Requires-Dist: pywin32==305; python_version == "3.6" and sys_platform == "win32"
Requires-Dist: pywin32==308; python_version > "3.6" and sys_platform == "win32"
Dynamic: author
Dynamic: author-email
Dynamic: classifier
Dynamic: description
Dynamic: description-content-type
Dynamic: download-url
Dynamic: license
Dynamic: license-file
Dynamic: provides-extra
Dynamic: requires-dist
Dynamic: summary
